{
  "metadata": {
    "lastUpdated": "2025-08-07T12:54:32Z",
    "currentVersion": "0.0.4",
    "projectType": "react",
    "totalReleases": 1
  },
  "releases": [
    {
      "version": "0.0.4",
      "project_type": "react",
      "date": "2025-08-07",
      "pr_number": 574,
      "raw_summary": "\"body_html\": \"\\nSummary by CodeRabbit\\n\\n\\nNew Features\\n\\n문서 게시글 작성 플로우가 2단계 폼으로 개편되어, 과목/수강년도/문서유형/커스텀 태그 선택 및 제목, 내용, 파일 첨부가 단계별로 진행됩니다.\\n문서 및 질문 게시판에 안내 문구가 추가되었습니다.\\n문서/질문 알림 전용 벨 아이콘이 추가되어, 헤더에서 구분된 알림을 확인할 수 있습니다.\\n문서 게시글 작성 시 익명(비공개) 설정 및 2000자 내용 입력이 지원됩니다.\\n커스텀 태그, 문서유형, 수강년도, 과목 등 선택 컴포넌트가 개선 및 신설되었습니다.\\n\\n\\n\\n개선 및 변경\\n\\n파일 업로드 UI가 개선되어, 첨부 파일 리스트 및 삭제가 직관적으로 변경되었습니다.\\n입력창, 텍스트에어리어, 버튼 등 주요 컴포넌트 스타일이 일관되게 리팩터링되었습니다.\\n문서/질문 작성 시 입력값 제한 및 유효성 검증 로직이 강화되었습니다.\\n헤더, 검색바, 플로팅버튼 등 UI 요소의 스타일 및 동작이 개선되었습니다.\\n\\n\\n\\n버그 수정\\n\\n질문 작성 시 줄바꿈 등 입력 동작이 자연스럽게 처리되도록 수정되었습니다.\\n\\n\\n\\n기타\\n\\n버전이 0.0.4로 업데이트되었습니다.\\n불필요하거나 구식 컴포넌트 및 API가 제거되고, 일부는 deprecated 디렉토리로 이동되었습니다.\\n2025년 수강년도가 추가되었습니다.\\n\\n\\n\\n\",\n  \"active_lock_reason\": null,\n  \"merged\": false,\n  \"mergeable\": true,\n  \"rebaseable\": true,\n  \"mergeable_state\": \"unstable\",\n  \"merged_by\": null,\n  \"comments\": 1,\n  \"review_comments\": 0,\n  \"maintainer_can_modify\": false,\n  \"commits\": 15,\n  \"additions\": 1270,\n  \"deletions\": 673,\n  \"changed_files\": 58\n}",
      "parsed_changes": {
        "new_features": [
          "문서 게시글 작성 플로우가 2단계 폼으로 개편되어, 과목/수강년도/문서유형/커스텀 태그 선택 및 제목, 내용, 파일 첨부가 단계별로 진행됩니다.",
          "문서 및 질문 게시판에 안내 문구가 추가되었습니다.",
          "문서/질문 알림 전용 벨 아이콘이 추가되어, 헤더에서 구분된 알림을 확인할 수 있습니다.",
          "문서 게시글 작성 시 익명(비공개) 설정 및 2000자 내용 입력이 지원됩니다.",
          "커스텀 태그, 문서유형, 수강년도, 과목 등 선택 컴포넌트가 개선 및 신설되었습니다."
        ],
        "개선_및_변경": [
          "파일 업로드 UI가 개선되어, 첨부 파일 리스트 및 삭제가 직관적으로 변경되었습니다.",
          "입력창, 텍스트에어리어, 버튼 등 주요 컴포넌트 스타일이 일관되게 리팩터링되었습니다.",
          "문서/질문 작성 시 입력값 제한 및 유효성 검증 로직이 강화되었습니다.",
          "헤더, 검색바, 플로팅버튼 등 UI 요소의 스타일 및 동작이 개선되었습니다."
        ],
        "버그_수정": ["질문 작성 시 줄바꿈 등 입력 동작이 자연스럽게 처리되도록 수정되었습니다."],
        "기타": [
          "버전이 0.0.4로 업데이트되었습니다.",
          "불필요하거나 구식 컴포넌트 및 API가 제거되고, 일부는 deprecated 디렉토리로 이동되었습니다.",
          "2025년 수강년도가 추가되었습니다."
        ]
      }
    }
  ]
}
